[
  {
    "id": "SUB0000",
    "beneficiario": "Empresa Tecnológica 0",
    "concepto": "I+D+i",
    "importe": 648594,
    "municipio": "Las Palmas",
    "provincia": "Sevilla",
    "fecha": "16/08/2025",
    "ministerio": "Ministerio de Educación"
  },
  {
    "id": "SUB0001",
    "beneficiario": "Empresa Constructora 1",
    "concepto": "Digitalización PYME",
    "importe": 1543951,
    "municipio": "Córdoba",
    "provincia": "Valencia",
    "fecha": "19/09/2025",
    "ministerio": "Ministerio del Interior"
  },
  {
    "id": "SUB0002",
    "beneficiario": "Empresa Constructora 2",
    "concepto": "I+D+i",
    "importe": 4111584,
    "municipio": "Córdoba",
    "provincia": "Barcelona",
    "fecha": "25/02/2025",
    "ministerio": "Ministerio de Hacienda"
  },
  {
    "id": "SUB0003",
    "beneficiario": "Empresa Tecnológica 3",
    "concepto": "Eficiencia energética",
    "importe": 3927222,
    "municipio": "Alicante",
    "provincia": "Madrid",
    "fecha": "24/05/2025",
    "ministerio": "Ministerio de Transportes"
  },
  {
    "id": "SUB0004",
    "beneficiario": "Empresa Tecnológica 4",
    "concepto": "I+D+i",
    "importe": 2735994,
    "municipio": "Sevilla",
    "provincia": "Barcelona",
    "fecha": "15/09/2025",
    "ministerio": "Ministerio de Transportes"
  },
  {
    "id": "SUB0005",
    "beneficiario": "Empresa Tecnológica 5",
    "concepto": "I+D+i",
    "importe": 1296490,
    "municipio": "Valencia",
    "provincia": "Sevilla",
    "fecha": "17/12/2025",
    "ministerio": "Ministerio de Transportes"
  },
  {
    "id": "SUB0006",
    "beneficiario": "Empresa Tecnológica 6",
    "concepto": "Contratación juvenil",
    "importe": 1897362,
    "municipio": "Zaragoza",
    "provincia": "Sevilla",
    "fecha": "26/12/2025",
    "ministerio": "Ministerio de Transportes"
  },
  {
    "id": "SUB0007",
    "beneficiario": "Empresa Industrial 7",
    "concepto": "Digitalización PYME",
    "importe": 3729053,
    "municipio": "Vigo",
    "provincia": "Madrid",
    "fecha": "27/06/2025",
    "ministerio": "Ministerio de Defensa"
  },
  {
    "id": "SUB0008",
    "beneficiario": "Empresa Industrial 8",
    "concepto": "Eficiencia energética",
    "importe": 4315471,
    "municipio": "Valencia",
    "provincia": "Sevilla",
    "fecha": "16/02/2026",
    "ministerio": "Ministerio de Educación"
  },
  {
    "id": "SUB0009",
    "beneficiario": "Empresa Constructora 9",
    "concepto": "Formación profesional",
    "importe": 3116377,
    "municipio": "Valladolid",
    "provincia": "Barcelona",
    "fecha": "26/12/2025",
    "ministerio": "Ministerio del Interior"
  },
  {
    "id": "SUB0010",
    "beneficiario": "Empresa Servicios 10",
    "concepto": "Formación profesional",
    "importe": 2830036,
    "municipio": "Las Palmas",
    "provincia": "Sevilla",
    "fecha": "28/02/2025",
    "ministerio": "Ministerio de Defensa"
  },
  {
    "id": "SUB0011",
    "beneficiario": "Empresa Constructora 11",
    "concepto": "I+D+i",
    "importe": 1082535,
    "municipio": "Madrid",
    "provincia": "Madrid",
    "fecha": "02/02/2026",
    "ministerio": "Ministerio de Hacienda"
  },
  {
    "id": "SUB0012",
    "beneficiario": "Empresa Tecnológica 12",
    "concepto": "Eficiencia energética",
    "importe": 4282404,
    "municipio": "Valencia",
    "provincia": "Valencia",
    "fecha": "17/02/2026",
    "ministerio": "Ministerio de Sanidad"
  },
  {
    "id": "SUB0013",
    "beneficiario": "Empresa Constructora 13",
    "concepto": "Eficiencia energética",
    "importe": 3886982,
    "municipio": "Alicante",
    "provincia": "Madrid",
    "fecha": "02/08/2025",
    "ministerio": "Ministerio de Defensa"
  },
  {
    "id": "SUB0014",
    "beneficiario": "Empresa Constructora 14",
    "concepto": "Digitalización PYME",
    "importe": 4196299,
    "municipio": "Palma",
    "provincia": "Barcelona",
    "fecha": "28/08/2025",
    "ministerio": "Ministerio de Sanidad"
  },
  {
    "id": "SUB0015",
    "beneficiario": "Empresa Tecnológica 15",
    "concepto": "Internacionalización",
    "importe": 404244,
    "municipio": "Valencia",
    "provincia": "Barcelona",
    "fecha": "30/05/2025",
    "ministerio": "Ministerio de Defensa"
  },
  {
    "id": "SUB0016",
    "beneficiario": "Empresa Servicios 16",
    "concepto": "Digitalización PYME",
    "importe": 303363,
    "municipio": "Valladolid",
    "provincia": "Madrid",
    "fecha": "23/12/2025",
    "ministerio": "Ministerio de Educación"
  },
  {
    "id": "SUB0017",
    "beneficiario": "Empresa Tecnológica 17",
    "concepto": "I+D+i",
    "importe": 2188834,
    "municipio": "Valladolid",
    "provincia": "Sevilla",
    "fecha": "15/05/2025",
    "ministerio": "Ministerio de Hacienda"
  },
  {
    "id": "SUB0018",
    "beneficiario": "Empresa Tecnológica 18",
    "concepto": "Formación profesional",
    "importe": 178978,
    "municipio": "Murcia",
    "provincia": "Valencia",
    "fecha": "26/06/2025",
    "ministerio": "Ministerio de Sanidad"
  },
  {
    "id": "SUB0019",
    "beneficiario": "Empresa Industrial 19",
    "concepto": "Internacionalización",
    "importe": 3724829,
    "municipio": "Málaga",
    "provincia": "Valencia",
    "fecha": "12/04/2025",
    "ministerio": "Ministerio de Hacienda"
  },
  {
    "id": "SUB0020",
    "beneficiario": "Empresa Tecnológica 20",
    "concepto": "Digitalización PYME",
    "importe": 2147908,
    "municipio": "Barcelona",
    "provincia": "Barcelona",
    "fecha": "18/04/2025",
    "ministerio": "Ministerio de Defensa"
  },
  {
    "id": "SUB0021",
    "beneficiario": "Empresa Industrial 21",
    "concepto": "Eficiencia energética",
    "importe": 3616661,
    "municipio": "Sevilla",
    "provincia": "Madrid",
    "fecha": "17/12/2025",
    "ministerio": "Ministerio de Educación"
  },
  {
    "id": "SUB0022",
    "beneficiario": "Empresa Constructora 22",
    "concepto": "Formación profesional",
    "importe": 711900,
    "municipio": "Murcia",
    "provincia": "Sevilla",
    "fecha": "10/04/2025",
    "ministerio": "Ministerio de Transportes"
  },
  {
    "id": "SUB0023",
    "beneficiario": "Empresa Constructora 23",
    "concepto": "Internacionalización",
    "importe": 1099718,
    "municipio": "Valladolid",
    "provincia": "Madrid",
    "fecha": "25/10/2025",
    "ministerio": "Ministerio de Defensa"
  },
  {
    "id": "SUB0024",
    "beneficiario": "Empresa Constructora 24",
    "concepto": "Formación profesional",
    "importe": 2939005,
    "municipio": "Valladolid",
    "provincia": "Sevilla",
    "fecha": "24/05/2025",
    "ministerio": "Ministerio de Educación"
  },
  {
    "id": "SUB0025",
    "beneficiario": "Empresa Constructora 25",
    "concepto": "Digitalización PYME",
    "importe": 2296565,
    "municipio": "Palma",
    "provincia": "Valencia",
    "fecha": "15/05/2025",
    "ministerio": "Ministerio de Hacienda"
  },
  {
    "id": "SUB0026",
    "beneficiario": "Empresa Industrial 26",
    "concepto": "Internacionalización",
    "importe": 1408698,
    "municipio": "Vigo",
    "provincia": "Sevilla",
    "fecha": "01/01/2026",
    "ministerio": "Ministerio del Interior"
  },
  {
    "id": "SUB0027",
    "beneficiario": "Empresa Constructora 27",
    "concepto": "Formación profesional",
    "importe": 1906207,
    "municipio": "Bilbao",
    "provincia": "Valencia",
    "fecha": "12/03/2025",
    "ministerio": "Ministerio de Transportes"
  },
  {
    "id": "SUB0028",
    "beneficiario": "Empresa Industrial 28",
    "concepto": "Contratación juvenil",
    "importe": 2413576,
    "municipio": "Málaga",
    "provincia": "Barcelona",
    "fecha": "25/09/2025",
    "ministerio": "Ministerio de Transportes"
  },
  {
    "id": "SUB0029",
    "beneficiario": "Empresa Constructora 29",
    "concepto": "Formación profesional",
    "importe": 4815616,
    "municipio": "Barcelona",
    "provincia": "Barcelona",
    "fecha": "08/03/2025",
    "ministerio": "Ministerio de Hacienda"
  },
  {
    "id": "SUB0030",
    "beneficiario": "Empresa Industrial 30",
    "concepto": "I+D+i",
    "importe": 697922,
    "municipio": "Vigo",
    "provincia": "Valencia",
    "fecha": "01/03/2025",
    "ministerio": "Ministerio de Defensa"
  },
  {
    "id": "SUB0031",
    "beneficiario": "Empresa Tecnológica 31",
    "concepto": "I+D+i",
    "importe": 2635484,
    "municipio": "Córdoba",
    "provincia": "Valencia",
    "fecha": "19/02/2026",
    "ministerio": "Ministerio del Interior"
  },
  {
    "id": "SUB0032",
    "beneficiario": "Empresa Constructora 32",
    "concepto": "I+D+i",
    "importe": 1217245,
    "municipio": "Murcia",
    "provincia": "Sevilla",
    "fecha": "09/06/2025",
    "ministerio": "Ministerio de Transportes"
  },
  {
    "id": "SUB0033",
    "beneficiario": "Empresa Industrial 33",
    "concepto": "Digitalización PYME",
    "importe": 1091122,
    "municipio": "Sevilla",
    "provincia": "Sevilla",
    "fecha": "30/04/2025",
    "ministerio": "Ministerio del Interior"
  },
  {
    "id": "SUB0034",
    "beneficiario": "Empresa Tecnológica 34",
    "concepto": "Contratación juvenil",
    "importe": 1877319,
    "municipio": "Valladolid",
    "provincia": "Madrid",
    "fecha": "14/05/2025",
    "ministerio": "Ministerio de Sanidad"
  },
  {
    "id": "SUB0035",
    "beneficiario": "Empresa Servicios 35",
    "concepto": "Internacionalización",
    "importe": 1627983,
    "municipio": "Las Palmas",
    "provincia": "Barcelona",
    "fecha": "01/07/2025",
    "ministerio": "Ministerio de Defensa"
  },
  {
    "id": "SUB0036",
    "beneficiario": "Empresa Industrial 36",
    "concepto": "Digitalización PYME",
    "importe": 641397,
    "municipio": "Madrid",
    "provincia": "Madrid",
    "fecha": "23/05/2025",
    "ministerio": "Ministerio de Defensa"
  },
  {
    "id": "SUB0037",
    "beneficiario": "Empresa Industrial 37",
    "concepto": "Eficiencia energética",
    "importe": 2621975,
    "municipio": "Madrid",
    "provincia": "Madrid",
    "fecha": "18/08/2025",
    "ministerio": "Ministerio de Sanidad"
  },
  {
    "id": "SUB0038",
    "beneficiario": "Empresa Constructora 38",
    "concepto": "Formación profesional",
    "importe": 4693551,
    "municipio": "Barcelona",
    "provincia": "Barcelona",
    "fecha": "03/01/2026",
    "ministerio": "Ministerio de Sanidad"
  },
  {
    "id": "SUB0039",
    "beneficiario": "Empresa Tecnológica 39",
    "concepto": "I+D+i",
    "importe": 1302671,
    "municipio": "Valencia",
    "provincia": "Barcelona",
    "fecha": "25/06/2025",
    "ministerio": "Ministerio de Defensa"
  },
  {
    "id": "SUB0040",
    "beneficiario": "Empresa Industrial 40",
    "concepto": "Digitalización PYME",
    "importe": 2821781,
    "municipio": "Las Palmas",
    "provincia": "Sevilla",
    "fecha": "24/09/2025",
    "ministerio": "Ministerio de Sanidad"
  },
  {
    "id": "SUB0041",
    "beneficiario": "Empresa Servicios 41",
    "concepto": "Contratación juvenil",
    "importe": 2881406,
    "municipio": "Zaragoza",
    "provincia": "Sevilla",
    "fecha": "16/01/2026",
    "ministerio": "Ministerio de Hacienda"
  },
  {
    "id": "SUB0042",
    "beneficiario": "Empresa Industrial 42",
    "concepto": "Digitalización PYME",
    "importe": 4307437,
    "municipio": "Córdoba",
    "provincia": "Barcelona",
    "fecha": "03/03/2025",
    "ministerio": "Ministerio de Hacienda"
  },
  {
    "id": "SUB0043",
    "beneficiario": "Empresa Constructora 43",
    "concepto": "Contratación juvenil",
    "importe": 3818265,
    "municipio": "Madrid",
    "provincia": "Madrid",
    "fecha": "25/12/2025",
    "ministerio": "Ministerio del Interior"
  },
  {
    "id": "SUB0044",
    "beneficiario": "Empresa Servicios 44",
    "concepto": "Internacionalización",
    "importe": 1940910,
    "municipio": "Valencia",
    "provincia": "Valencia",
    "fecha": "28/08/2025",
    "ministerio": "Ministerio de Defensa"
  },
  {
    "id": "SUB0045",
    "beneficiario": "Empresa Industrial 45",
    "concepto": "Digitalización PYME",
    "importe": 351746,
    "municipio": "Málaga",
    "provincia": "Valencia",
    "fecha": "29/05/2025",
    "ministerio": "Ministerio de Transportes"
  },
  {
    "id": "SUB0046",
    "beneficiario": "Empresa Constructora 46",
    "concepto": "Digitalización PYME",
    "importe": 576813,
    "municipio": "Bilbao",
    "provincia": "Barcelona",
    "fecha": "07/02/2026",
    "ministerio": "Ministerio de Transportes"
  },
  {
    "id": "SUB0047",
    "beneficiario": "Empresa Tecnológica 47",
    "concepto": "Contratación juvenil",
    "importe": 4736091,
    "municipio": "Madrid",
    "provincia": "Madrid",
    "fecha": "07/05/2025",
    "ministerio": "Ministerio del Interior"
  },
  {
    "id": "SUB0048",
    "beneficiario": "Empresa Industrial 48",
    "concepto": "Eficiencia energética",
    "importe": 1618823,
    "municipio": "Sevilla",
    "provincia": "Madrid",
    "fecha": "04/02/2026",
    "ministerio": "Ministerio de Defensa"
  },
  {
    "id": "SUB0049",
    "beneficiario": "Empresa Tecnológica 49",
    "concepto": "Digitalización PYME",
    "importe": 2372930,
    "municipio": "Córdoba",
    "provincia": "Valencia",
    "fecha": "25/06/2025",
    "ministerio": "Ministerio del Interior"
  },
  {
    "id": "SUB0050",
    "beneficiario": "Empresa Industrial 50",
    "concepto": "Digitalización PYME",
    "importe": 383363,
    "municipio": "Gijón",
    "provincia": "Barcelona",
    "fecha": "16/09/2025",
    "ministerio": "Ministerio de Hacienda"
  },
  {
    "id": "SUB0051",
    "beneficiario": "Empresa Industrial 51",
    "concepto": "Contratación juvenil",
    "importe": 1223516,
    "municipio": "Bilbao",
    "provincia": "Sevilla",
    "fecha": "22/05/2025",
    "ministerio": "Ministerio de Educación"
  },
  {
    "id": "SUB0052",
    "beneficiario": "Empresa Constructora 52",
    "concepto": "Eficiencia energética",
    "importe": 1705835,
    "municipio": "Gijón",
    "provincia": "Sevilla",
    "fecha": "10/08/2025",
    "ministerio": "Ministerio de Defensa"
  },
  {
    "id": "SUB0053",
    "beneficiario": "Empresa Industrial 53",
    "concepto": "Formación profesional",
    "importe": 1913866,
    "municipio": "Sevilla",
    "provincia": "Barcelona",
    "fecha": "10/06/2025",
    "ministerio": "Ministerio de Sanidad"
  },
  {
    "id": "SUB0054",
    "beneficiario": "Empresa Tecnológica 54",
    "concepto": "Internacionalización",
    "importe": 3984752,
    "municipio": "Murcia",
    "provincia": "Valencia",
    "fecha": "04/06/2025",
    "ministerio": "Ministerio de Hacienda"
  },
  {
    "id": "SUB0055",
    "beneficiario": "Empresa Tecnológica 55",
    "concepto": "Eficiencia energética",
    "importe": 3962351,
    "municipio": "Valencia",
    "provincia": "Sevilla",
    "fecha": "15/07/2025",
    "ministerio": "Ministerio de Sanidad"
  },
  {
    "id": "SUB0056",
    "beneficiario": "Empresa Industrial 56",
    "concepto": "Contratación juvenil",
    "importe": 3437189,
    "municipio": "Málaga",
    "provincia": "Valencia",
    "fecha": "27/08/2025",
    "ministerio": "Ministerio del Interior"
  },
  {
    "id": "SUB0057",
    "beneficiario": "Empresa Constructora 57",
    "concepto": "Eficiencia energética",
    "importe": 4519927,
    "municipio": "Vigo",
    "provincia": "Barcelona",
    "fecha": "20/04/2025",
    "ministerio": "Ministerio de Hacienda"
  },
  {
    "id": "SUB0058",
    "beneficiario": "Empresa Constructora 58",
    "concepto": "Formación profesional",
    "importe": 155300,
    "municipio": "Barcelona",
    "provincia": "Barcelona",
    "fecha": "10/05/2025",
    "ministerio": "Ministerio de Transportes"
  },
  {
    "id": "SUB0059",
    "beneficiario": "Empresa Servicios 59",
    "concepto": "Contratación juvenil",
    "importe": 4712331,
    "municipio": "Madrid",
    "provincia": "Madrid",
    "fecha": "10/02/2026",
    "ministerio": "Ministerio de Defensa"
  },
  {
    "id": "SUB0060",
    "beneficiario": "Empresa Tecnológica 60",
    "concepto": "Formación profesional",
    "importe": 2934635,
    "municipio": "Alicante",
    "provincia": "Sevilla",
    "fecha": "18/01/2026",
    "ministerio": "Ministerio de Educación"
  },
  {
    "id": "SUB0061",
    "beneficiario": "Empresa Servicios 61",
    "concepto": "I+D+i",
    "importe": 752266,
    "municipio": "Córdoba",
    "provincia": "Sevilla",
    "fecha": "02/09/2025",
    "ministerio": "Ministerio de Transportes"
  },
  {
    "id": "SUB0062",
    "beneficiario": "Empresa Servicios 62",
    "concepto": "I+D+i",
    "importe": 4524429,
    "municipio": "Sevilla",
    "provincia": "Barcelona",
    "fecha": "25/01/2026",
    "ministerio": "Ministerio de Sanidad"
  },
  {
    "id": "SUB0063",
    "beneficiario": "Empresa Servicios 63",
    "concepto": "I+D+i",
    "importe": 3542987,
    "municipio": "Las Palmas",
    "provincia": "Sevilla",
    "fecha": "06/05/2025",
    "ministerio": "Ministerio de Hacienda"
  },
  {
    "id": "SUB0064",
    "beneficiario": "Empresa Industrial 64",
    "concepto": "Digitalización PYME",
    "importe": 840710,
    "municipio": "Alicante",
    "provincia": "Sevilla",
    "fecha": "18/08/2025",
    "ministerio": "Ministerio de Sanidad"
  },
  {
    "id": "SUB0065",
    "beneficiario": "Empresa Tecnológica 65",
    "concepto": "Formación profesional",
    "importe": 1511825,
    "municipio": "Murcia",
    "provincia": "Barcelona",
    "fecha": "05/11/2025",
    "ministerio": "Ministerio de Sanidad"
  },
  {
    "id": "SUB0066",
    "beneficiario": "Empresa Tecnológica 66",
    "concepto": "Internacionalización",
    "importe": 2236439,
    "municipio": "Córdoba",
    "provincia": "Barcelona",
    "fecha": "31/01/2026",
    "ministerio": "Ministerio de Hacienda"
  },
  {
    "id": "SUB0067",
    "beneficiario": "Empresa Industrial 67",
    "concepto": "Internacionalización",
    "importe": 3746246,
    "municipio": "Murcia",
    "provincia": "Sevilla",
    "fecha": "17/01/2026",
    "ministerio": "Ministerio de Sanidad"
  },
  {
    "id": "SUB0068",
    "beneficiario": "Empresa Industrial 68",
    "concepto": "I+D+i",
    "importe": 4691925,
    "municipio": "Sevilla",
    "provincia": "Sevilla",
    "fecha": "18/11/2025",
    "ministerio": "Ministerio de Hacienda"
  },
  {
    "id": "SUB0069",
    "beneficiario": "Empresa Constructora 69",
    "concepto": "Formación profesional",
    "importe": 1026180,
    "municipio": "Málaga",
    "provincia": "Valencia",
    "fecha": "11/05/2025",
    "ministerio": "Ministerio del Interior"
  },
  {
    "id": "SUB0070",
    "beneficiario": "Empresa Industrial 70",
    "concepto": "Contratación juvenil",
    "importe": 1844195,
    "municipio": "Alicante",
    "provincia": "Barcelona",
    "fecha": "05/07/2025",
    "ministerio": "Ministerio de Transportes"
  },
  {
    "id": "SUB0071",
    "beneficiario": "Empresa Servicios 71",
    "concepto": "Formación profesional",
    "importe": 1771390,
    "municipio": "Valladolid",
    "provincia": "Madrid",
    "fecha": "02/05/2025",
    "ministerio": "Ministerio de Transportes"
  },
  {
    "id": "SUB0072",
    "beneficiario": "Empresa Tecnológica 72",
    "concepto": "Eficiencia energética",
    "importe": 1412752,
    "municipio": "Gijón",
    "provincia": "Madrid",
    "fecha": "21/03/2025",
    "ministerio": "Ministerio de Sanidad"
  },
  {
    "id": "SUB0073",
    "beneficiario": "Empresa Constructora 73",
    "concepto": "Contratación juvenil",
    "importe": 658631,
    "municipio": "Málaga",
    "provincia": "Madrid",
    "fecha": "20/02/2025",
    "ministerio": "Ministerio del Interior"
  },
  {
    "id": "SUB0074",
    "beneficiario": "Empresa Constructora 74",
    "concepto": "I+D+i",
    "importe": 3411850,
    "municipio": "Sevilla",
    "provincia": "Madrid",
    "fecha": "22/01/2026",
    "ministerio": "Ministerio del Interior"
  },
  {
    "id": "SUB0075",
    "beneficiario": "Empresa Tecnológica 75",
    "concepto": "Formación profesional",
    "importe": 626864,
    "municipio": "Sevilla",
    "provincia": "Valencia",
    "fecha": "13/09/2025",
    "ministerio": "Ministerio de Defensa"
  },
  {
    "id": "SUB0076",
    "beneficiario": "Empresa Industrial 76",
    "concepto": "Eficiencia energética",
    "importe": 3267206,
    "municipio": "Málaga",
    "provincia": "Valencia",
    "fecha": "13/01/2026",
    "ministerio": "Ministerio del Interior"
  },
  {
    "id": "SUB0077",
    "beneficiario": "Empresa Servicios 77",
    "concepto": "Internacionalización",
    "importe": 4085242,
    "municipio": "Barcelona",
    "provincia": "Barcelona",
    "fecha": "29/08/2025",
    "ministerio": "Ministerio de Defensa"
  },
  {
    "id": "SUB0078",
    "beneficiario": "Empresa Tecnológica 78",
    "concepto": "Eficiencia energética",
    "importe": 1495297,
    "municipio": "Valencia",
    "provincia": "Madrid",
    "fecha": "08/11/2025",
    "ministerio": "Ministerio de Transportes"
  },
  {
    "id": "SUB0079",
    "beneficiario": "Empresa Constructora 79",
    "concepto": "Contratación juvenil",
    "importe": 3267325,
    "municipio": "Las Palmas",
    "provincia": "Valencia",
    "fecha": "13/08/2025",
    "ministerio": "Ministerio de Transportes"
  },
  {
    "id": "SUB0080",
    "beneficiario": "Empresa Tecnológica 80",
    "concepto": "Digitalización PYME",
    "importe": 535106,
    "municipio": "Gijón",
    "provincia": "Valencia",
    "fecha": "12/02/2026",
    "ministerio": "Ministerio de Educación"
  },
  {
    "id": "SUB0081",
    "beneficiario": "Empresa Industrial 81",
    "concepto": "Internacionalización",
    "importe": 1379173,
    "municipio": "Córdoba",
    "provincia": "Valencia",
    "fecha": "20/10/2025",
    "ministerio": "Ministerio de Defensa"
  },
  {
    "id": "SUB0082",
    "beneficiario": "Empresa Servicios 82",
    "concepto": "Internacionalización",
    "importe": 488757,
    "municipio": "Zaragoza",
    "provincia": "Valencia",
    "fecha": "21/01/2026",
    "ministerio": "Ministerio de Hacienda"
  },
  {
    "id": "SUB0083",
    "beneficiario": "Empresa Constructora 83",
    "concepto": "Eficiencia energética",
    "importe": 3695743,
    "municipio": "Palma",
    "provincia": "Valencia",
    "fecha": "25/10/2025",
    "ministerio": "Ministerio de Sanidad"
  },
  {
    "id": "SUB0084",
    "beneficiario": "Empresa Constructora 84",
    "concepto": "Contratación juvenil",
    "importe": 1655863,
    "municipio": "Zaragoza",
    "provincia": "Barcelona",
    "fecha": "26/03/2025",
    "ministerio": "Ministerio del Interior"
  },
  {
    "id": "SUB0085",
    "beneficiario": "Empresa Tecnológica 85",
    "concepto": "Contratación juvenil",
    "importe": 2442323,
    "municipio": "Las Palmas",
    "provincia": "Barcelona",
    "fecha": "13/07/2025",
    "ministerio": "Ministerio de Sanidad"
  },
  {
    "id": "SUB0086",
    "beneficiario": "Empresa Industrial 86",
    "concepto": "Digitalización PYME",
    "importe": 51508,
    "municipio": "Alicante",
    "provincia": "Madrid",
    "fecha": "27/03/2025",
    "ministerio": "Ministerio de Sanidad"
  },
  {
    "id": "SUB0087",
    "beneficiario": "Empresa Constructora 87",
    "concepto": "Contratación juvenil",
    "importe": 1308003,
    "municipio": "Córdoba",
    "provincia": "Sevilla",
    "fecha": "27/03/2025",
    "ministerio": "Ministerio de Hacienda"
  },
  {
    "id": "SUB0088",
    "beneficiario": "Empresa Servicios 88",
    "concepto": "Eficiencia energética",
    "importe": 4195473,
    "municipio": "Bilbao",
    "provincia": "Madrid",
    "fecha": "24/01/2026",
    "ministerio": "Ministerio de Educación"
  },
  {
    "id": "SUB0089",
    "beneficiario": "Empresa Constructora 89",
    "concepto": "Internacionalización",
    "importe": 2382993,
    "municipio": "Gijón",
    "provincia": "Madrid",
    "fecha": "22/12/2025",
    "ministerio": "Ministerio del Interior"
  },
  {
    "id": "SUB0090",
    "beneficiario": "Empresa Servicios 90",
    "concepto": "Contratación juvenil",
    "importe": 400014,
    "municipio": "Alicante",
    "provincia": "Sevilla",
    "fecha": "05/02/2026",
    "ministerio": "Ministerio de Transportes"
  },
  {
    "id": "SUB0091",
    "beneficiario": "Empresa Servicios 91",
    "concepto": "Formación profesional",
    "importe": 3062423,
    "municipio": "Barcelona",
    "provincia": "Barcelona",
    "fecha": "13/05/2025",
    "ministerio": "Ministerio del Interior"
  },
  {
    "id": "SUB0092",
    "beneficiario": "Empresa Servicios 92",
    "concepto": "Formación profesional",
    "importe": 4905829,
    "municipio": "Alicante",
    "provincia": "Madrid",
    "fecha": "19/03/2025",
    "ministerio": "Ministerio de Transportes"
  },
  {
    "id": "SUB0093",
    "beneficiario": "Empresa Constructora 93",
    "concepto": "Eficiencia energética",
    "importe": 3250045,
    "municipio": "Madrid",
    "provincia": "Madrid",
    "fecha": "30/04/2025",
    "ministerio": "Ministerio de Defensa"
  },
  {
    "id": "SUB0094",
    "beneficiario": "Empresa Servicios 94",
    "concepto": "Internacionalización",
    "importe": 1733270,
    "municipio": "Bilbao",
    "provincia": "Barcelona",
    "fecha": "05/04/2025",
    "ministerio": "Ministerio de Sanidad"
  },
  {
    "id": "SUB0095",
    "beneficiario": "Empresa Industrial 95",
    "concepto": "Internacionalización",
    "importe": 2453033,
    "municipio": "Madrid",
    "provincia": "Madrid",
    "fecha": "17/01/2026",
    "ministerio": "Ministerio de Transportes"
  },
  {
    "id": "SUB0096",
    "beneficiario": "Empresa Industrial 96",
    "concepto": "Eficiencia energética",
    "importe": 3140681,
    "municipio": "Madrid",
    "provincia": "Madrid",
    "fecha": "29/08/2025",
    "ministerio": "Ministerio de Educación"
  },
  {
    "id": "SUB0097",
    "beneficiario": "Empresa Tecnológica 97",
    "concepto": "Digitalización PYME",
    "importe": 3225151,
    "municipio": "Las Palmas",
    "provincia": "Barcelona",
    "fecha": "29/08/2025",
    "ministerio": "Ministerio de Educación"
  },
  {
    "id": "SUB0098",
    "beneficiario": "Empresa Tecnológica 98",
    "concepto": "Contratación juvenil",
    "importe": 1889309,
    "municipio": "Alicante",
    "provincia": "Madrid",
    "fecha": "27/08/2025",
    "ministerio": "Ministerio de Sanidad"
  },
  {
    "id": "SUB0099",
    "beneficiario": "Empresa Servicios 99",
    "concepto": "I+D+i",
    "importe": 1477308,
    "municipio": "Gijón",
    "provincia": "Sevilla",
    "fecha": "30/04/2025",
    "ministerio": "Ministerio de Transportes"
  }
]